ecommerce_django/__init__.py
ecommerce_django/asgi.py
ecommerce_django/settings.py
ecommerce_django/urls.py
ecommerce_django/wsgi.py
shopping/__init__.py
shopping/admin.py
shopping/apps.py
shopping/models.py
shopping/tests.py
shopping/urls.py
shopping/views.py
shopping/migrations/0001_initial.py
shopping/migrations/0002_auto_20201101_2309.py
shopping/migrations/0003_products_image.py
shopping/migrations/0004_payment.py
shopping/migrations/__init__.py
users/__init__.py
users/admin.py
users/apps.py
users/forms.py
users/models.py
users/tests.py
users/views.py
users/migrations/0001_initial.py
users/migrations/__init__.py
ecommerce_djangoxx-1.0.2.dist-info/LICENSE
ecommerce_djangoxx-1.0.2.dist-info/METADATA
ecommerce_djangoxx-1.0.2.dist-info/WHEEL
ecommerce_djangoxx-1.0.2.dist-info/top_level.txt
ecommerce_djangoxx-1.0.2.dist-info/RECORD
