Metadata-Version: 2.1
Name: ecommerce-djangoxx
Version: 1.0.2
Summary: Pthon ecommerce_django
Home-page: https://github.com/Kshitiz-Mhto/EPL-data-board
Author: Ibceberg
Author-email: ibergx00@gmail.com
License: https://www.apache.org/licenses/LICENSE-2.0
Classifier: License :: OSI Approved :: Apache Software License
Classifier: Programming Language :: Python :: 3.5
Classifier: Programming Language :: Python :: 3.6
Classifier: Programming Language :: Python :: 3.7
Requires-Python: >=3.5
License-File: LICENSE
